{
"skeleton": {
	"hash": "wdsI1+rIzccPJDllUAYIG79j99U",
	"spine": "3.8.99",
	"x": -669,
	"y": -513,
	"width": 1334,
	"height": 1024,
	"images": "C:/Users/ASUS/Desktop/Bakugan/Export/Transit",
	"audio": ""
},
"bones": [
	{ "name": "root" }
],
"slots": [
	{ "name": "100", "bone": "root", "attachment": "100" }
],
"skins": [
	{
		"name": "default",
		"attachments": {
			"100": {
				"100": { "x": -2, "y": -1, "width": 1334, "height": 1024 },
				"101": { "x": -2, "y": -1, "width": 1334, "height": 1024 },
				"102": { "x": -2, "y": -1, "width": 1334, "height": 1024 },
				"103": { "x": -2, "y": -1, "width": 1334, "height": 1024 },
				"104": { "x": -2, "y": -1, "width": 1334, "height": 1024 },
				"105": { "x": -2, "y": -1, "width": 1334, "height": 1024 },
				"106": { "x": -2, "y": -1, "width": 1334, "height": 1024 },
				"107": { "x": -2, "y": -1, "width": 1334, "height": 1024 },
				"108": { "x": -2, "y": -1, "width": 1334, "height": 1024 },
				"109": { "x": -2, "y": -1, "width": 1334, "height": 1024 },
				"110": { "x": -2, "y": -1, "width": 1334, "height": 1024 },
				"111": { "x": -2, "y": -1, "width": 1334, "height": 1024 },
				"112": { "x": -2, "y": -1, "width": 1334, "height": 1024 },
				"113": { "x": -2, "y": -1, "width": 1334, "height": 1024 },
				"114": { "x": -2, "y": -1, "width": 1334, "height": 1024 },
				"115": { "x": -2, "y": -1, "width": 1334, "height": 1024 },
				"116": { "x": -2, "y": -1, "width": 1334, "height": 1024 },
				"117": { "x": -2, "y": -1, "width": 1334, "height": 1024 },
				"118": { "x": -2, "y": -1, "width": 1334, "height": 1024 },
				"119": { "x": -2, "y": -1, "width": 1334, "height": 1024 },
				"120": { "x": -2, "y": -1, "width": 1334, "height": 1024 },
				"121": { "x": -2, "y": -1, "width": 1334, "height": 1024 },
				"122": { "x": -2, "y": -1, "width": 1334, "height": 1024 },
				"123": { "x": -2, "y": -1, "width": 1334, "height": 1024 },
				"124": { "x": -2, "y": -1, "width": 1334, "height": 1024 },
				"125": { "x": -2, "y": -1, "width": 1334, "height": 1024 },
				"126": { "x": -2, "y": -1, "width": 1334, "height": 1024 }
			}
		}
	}
],
"animations": {
	"animation": {
		"slots": {
			"100": {
				"attachment": [
					{ "time": 0.0333, "name": "101" },
					{ "time": 0.0667, "name": "102" },
					{ "time": 0.1, "name": "103" },
					{ "time": 0.1333, "name": "104" },
					{ "time": 0.1667, "name": "105" },
					{ "time": 0.2, "name": "106" },
					{ "time": 0.2333, "name": "107" },
					{ "time": 0.2667, "name": "108" },
					{ "time": 0.3, "name": "109" },
					{ "time": 0.3333, "name": "110" },
					{ "time": 0.3667, "name": "111" },
					{ "time": 0.4, "name": "112" },
					{ "time": 0.4333, "name": "113" },
					{ "time": 0.4667, "name": "114" },
					{ "time": 0.5, "name": "115" },
					{ "time": 0.5333, "name": "116" },
					{ "time": 0.5667, "name": "117" },
					{ "time": 0.6, "name": "118" },
					{ "time": 0.6333, "name": "119" },
					{ "time": 0.6667, "name": "120" },
					{ "time": 0.7, "name": "121" },
					{ "time": 0.7333, "name": "122" },
					{ "time": 0.7667, "name": "123" },
					{ "time": 0.8, "name": "124" },
					{ "time": 0.8333, "name": "125" },
					{ "time": 0.8667, "name": "126" }
				]
			}
		}
	}
}
}